seadance_transcript_sdk/__init__.py
seadance_transcript_sdk/client.py
seadance_transcript_sdk/constants.py
seadance_transcript_sdk/formatting.py
seadance_transcript_sdk/summary.py
seadance_transcript_sdk/transcript.py
seadance_transcript_sdk/types.py
seadanceai_transcript_sdk-0.1.1.dist-info/licenses/LICENSE
seadanceai_transcript_sdk-0.1.1.dist-info/METADATA
seadanceai_transcript_sdk-0.1.1.dist-info/WHEEL
seadanceai_transcript_sdk-0.1.1.dist-info/top_level.txt
seadanceai_transcript_sdk-0.1.1.dist-info/RECORD
