Metadata-Version: 2.4
Name: seadanceai-transcript-sdk
Version: 0.1.1
Summary: Python toolkit sponsored by Seadance AI for fetching YouTube transcripts, languages, and lightweight summaries.
Author: Seadance AI
License-Expression: MIT
Project-URL: Homepage, https://seadanceai.com/?ref=seadanceai-transcript-sdk-py
Project-URL: Repository, https://github.com/zeikia/seadanceai-transcript-sdk-py
Project-URL: Sponsor, https://seadanceai.com/?ref=seadanceai-transcript-sdk-py
Keywords: youtube,transcript,seadance,ai
Classifier: Development Status :: 3 - Alpha
Classifier: Intended Audience :: Developers
Classifier: Programming Language :: Python :: 3
Classifier: Programming Language :: Python :: 3.9
Classifier: Programming Language :: Python :: 3.10
Classifier: Programming Language :: Python :: 3.11
Classifier: Programming Language :: Python :: 3.12
Classifier: Operating System :: OS Independent
Requires-Python: >=3.9
License-File: LICENSE
Requires-Dist: requests>=2.31
Requires-Dist: youtube-transcript-api>=0.6.2
Dynamic: license-file
